[{"instanceType":"m5.2xlarge","region":"ap-south-1-ccu-1","priceModel":"onDemand","vcpu":8,"memory":32,"gpu":0,"unit":"Hrs","pricePerUnit":{"USD":"0.5450000000","CNY":""}},{"instanceType":"g4dn.2xlarge","region":"ap-south-1-ccu-1","priceModel":"onDemand","vcpu":8,"memory":32,"gpu":1,"unit":"Hrs","pricePerUnit":{"USD":"1.2000000000","CNY":""}},{"instanceType":"t3.medium","region":"ap-south-1-ccu-1","priceModel":"onDemand","vcpu":2,"memory":4,"gpu":0,"unit":"Hrs","pricePerUnit":{"USD":"0.0605000000","CNY":""}},{"instanceType":"c5.2xlarge","region":"ap-south-1-ccu-1","priceModel":"onDemand","vcpu":8,"memory":16,"gpu":0,"unit":"Hrs","pricePerUnit":{"USD":"0.4590000000","CNY":""}},{"instanceType":"c5.12xlarge","region":"ap-south-1-ccu-1","priceModel":"onDemand","vcpu":48,"memory":96,"gpu":0,"unit":"Hrs","pricePerUnit":{"USD":"2.7540000000","CNY":""}},{"instanceType":"r5.4xlarge","region":"ap-south-1-ccu-1","priceModel":"onDemand","vcpu":16,"memory":128,"gpu":0,"unit":"Hrs","pricePerUnit":{"USD":"1.4040000000","CNY":""}},{"instanceType":"t3.xlarge","region":"ap-south-1-ccu-1","priceModel":"onDemand","vcpu":4,"memory":16,"gpu":0,"unit":"Hrs","pricePerUnit":{"USD":"0.2419000000","CNY":""}},{"instanceType":"r5.2xlarge","region":"ap-south-1-ccu-1","priceModel":"onDemand","vcpu":8,"memory":64,"gpu":0,"unit":"Hrs","pricePerUnit":{"USD":"0.7020000000","CNY":""}}]