[{"instanceType":"t2.xlarge","region":"sa-east-1","priceModel":"onDemand","vcpu":4,"memory":16,"unit":"Hrs","pricePerUnit":{"USD":"0.2976000000","CNY":""}},{"instanceType":"m2.xlarge","region":"sa-east-1","priceModel":"onDemand","vcpu":2,"memory":17.1,"unit":"Hrs","pricePerUnit":{"USD":"0.3230000000","CNY":""}},{"instanceType":"r5n.metal","region":"sa-east-1","priceModel":"onDemand","vcpu":96,"memory":768,"unit":"Hrs","pricePerUnit":{"USD":"11.3280000000","CNY":""}},{"instanceType":"c6gd.2xlarge","region":"sa-east-1","priceModel":"onDemand","vcpu":8,"memory":16,"unit":"Hrs","pricePerUnit":{"USD":"0.4760000000","CNY":""}},{"instanceType":"m4.4xlarge","region":"sa-east-1","priceModel":"onDemand","vcpu":16,"memory":64,"unit":"Hrs","pricePerUnit":{"USD":"1.2720000000","CNY":""}},{"instanceType":"r5d.8xlarge","region":"sa-east-1","priceModel":"onDemand","vcpu":32,"memory":256,"unit":"Hrs","pricePerUnit":{"USD":"3.6480000000","CNY":""}},{"instanceType":"i4i.metal","region":"sa-east-1","priceModel":"onDemand","vcpu":128,"memory":1024,"unit":"Hrs","pricePerUnit":{"USD":"17.5300000000","CNY":""}},{"instanceType":"c5ad.xlarge","region":"sa-east-1","priceModel":"onDemand","vcpu":4,"memory":8,"unit":"Hrs","pricePerUnit":{"USD":"0.2680000000","CNY":""}},{"instanceType":"m6gd.metal","region":"sa-east-1","priceModel":"onDemand","vcpu":64,"memory":256,"unit":"Hrs","pricePerUnit":{"USD":"4.6080000000","CNY":""}},{"instanceType":"t3a.micro","region":"sa-east-1","priceModel":"onDemand","vcpu":2,"memory":1,"unit":"Hrs","pricePerUnit":{"USD":"0.0151000000","CNY":""}},{"instanceType":"inf1.6xlarge","region":"sa-east-1","priceModel":"onDemand","vcpu":24,"memory":48,"unit":"Hrs","pricePerUnit":{"USD":"1.9500000000","CNY":""}},{"instanceType":"x2iedn.16xlarge","region":"sa-east-1","priceModel":"onDemand","vcpu":64,"memory":2048,"unit":"Hrs","pricePerUnit":{"USD":"26.0100000000","CNY":""}},{"instanceType":"i3.8xlarge","region":"sa-east-1","priceModel":"onDemand","vcpu":32,"memory":244,"unit":"Hrs","pricePerUnit":{"USD":"3.9840000000","CNY":""}},{"instanceType":"m5a.12xlarge","region":"sa-east-1","priceModel":"onDemand","vcpu":48,"memory":192,"unit":"Hrs","pricePerUnit":{"USD":"3.3120000000","CNY":""}},{"instanceType":"c5n.2xlarge","region":"sa-east-1","priceModel":"onDemand","vcpu":8,"memory":21,"unit":"Hrs","pricePerUnit":{"USD":"0.6640000000","CNY":""}},{"instanceType":"c6g.large","region":"sa-east-1","priceModel":"onDemand","vcpu":2,"memory":4,"unit":"Hrs","pricePerUnit":{"USD":"0.1048000000","CNY":""}},{"instanceType":"r5d.16xlarge","region":"sa-east-1","priceModel":"onDemand","vcpu":64,"memory":512,"unit":"Hrs","pricePerUnit":{"USD":"7.2960000000","CNY":""}},{"instanceType":"r5a.16xlarge","region":"sa-east-1","priceModel":"onDemand","vcpu":64,"memory":512,"unit":"Hrs","pricePerUnit":{"USD":"5.7920000000","CNY":""}},{"instanceType":"m6gd.12xlarge","region":"sa-east-1","priceModel":"onDemand","vcpu":48,"memory":192,"unit":"Hrs","pricePerUnit":{"USD":"3.4560000000","CNY":""}},{"instanceType":"c5n.9xlarge","region":"sa-east-1","priceModel":"onDemand","vcpu":36,"memory":96,"unit":"Hrs","pricePerUnit":{"USD":"2.9880000000","CNY":""}},{"instanceType":"m6g.large","region":"sa-east-1","priceModel":"onDemand","vcpu":2,"memory":8,"unit":"Hrs","pricePerUnit":{"USD":"0.1224000000","CNY":""}},{"instanceType":"r6i.24xlarge","region":"sa-east-1","priceModel":"onDemand","vcpu":96,"memory":768,"unit":"Hrs","pricePerUnit":{"USD":"9.6480000000","CNY":""}},{"instanceType":"m5ad.24xlarge","region":"sa-east-1","priceModel":"onDemand","vcpu":96,"memory":384,"unit":"Hrs","pricePerUnit":{"USD":"7.9200000000","CNY":""}},{"instanceType":"c5ad.12xlarge","region":"sa-east-1","priceModel":"onDemand","vcpu":48,"memory":96,"unit":"Hrs","pricePerUnit":{"USD":"3.2160000000","CNY":""}},{"instanceType":"t3.2xlarge","region":"sa-east-1","priceModel":"onDemand","vcpu":8,"memory":32,"unit":"Hrs","pricePerUnit":{"USD":"0.5376000000","CNY":""}},{"instanceType":"r5b.16xlarge","region":"sa-east-1","priceModel":"onDemand","vcpu":64,"memory":512,"unit":"Hrs","pricePerUnit":{"USD":"7.5840000000","CNY":""}},{"instanceType":"c6gn.2xlarge","region":"sa-east-1","priceModel":"onDemand","vcpu":8,"memory":16,"unit":"Hrs","pricePerUnit":{"USD":"0.5320000000","CNY":""}},{"instanceType":"i4i.12xlarge","region":"sa-east-1","priceModel":"onDemand","vcpu":48,"memory":384,"unit":"Hrs","pricePerUnit":{"USD":"6.5740000000","CNY":""}},{"instanceType":"c5a.16xlarge","region":"sa-east-1","priceModel":"onDemand","vcpu":64,"memory":128,"unit":"Hrs","pricePerUnit":{"USD":"3.7760000000","CNY":""}},{"instanceType":"x2idn.32xlarge","region":"sa-east-1","priceModel":"onDemand","vcpu":128,"memory":2048,"unit":"Hrs","pricePerUnit":{"USD":"26.0100000000","CNY":""}},{"instanceType":"c4.xlarge","region":"sa-east-1","priceModel":"onDemand","vcpu":4,"memory":7.5,"unit":"Hrs","pricePerUnit":{"USD":"0.3090000000","CNY":""}},{"instanceType":"t3.micro","region":"sa-east-1","priceModel":"onDemand","vcpu":2,"memory":1,"unit":"Hrs","pricePerUnit":{"USD":"0.0168000000","CNY":""}},{"instanceType":"x2iedn.metal","region":"sa-east-1","priceModel":"onDemand","vcpu":128,"memory":4096,"unit":"Hrs","pricePerUnit":{"USD":"52.0200000000","CNY":""}},{"instanceType":"c4.4xlarge","region":"sa-east-1","priceModel":"onDemand","vcpu":16,"memory":30,"unit":"Hrs","pricePerUnit":{"USD":"1.2350000000","CNY":""}},{"instanceType":"r6i.4xlarge","region":"sa-east-1","priceModel":"onDemand","vcpu":16,"memory":128,"unit":"Hrs","pricePerUnit":{"USD":"1.6080000000","CNY":""}},{"instanceType":"r5d.24xlarge","region":"sa-east-1","priceModel":"onDemand","vcpu":96,"memory":768,"unit":"Hrs","pricePerUnit":{"USD":"10.9440000000","CNY":""}},{"instanceType":"m6i.metal","region":"sa-east-1","priceModel":"onDemand","vcpu":128,"memory":512,"unit":"Hrs","pricePerUnit":{"USD":"9.7920000000","CNY":""}},{"instanceType":"r6i.12xlarge","region":"sa-east-1","priceModel":"onDemand","vcpu":48,"memory":384,"unit":"Hrs","pricePerUnit":{"USD":"4.8240000000","CNY":""}},{"instanceType":"r3.xlarge","region":"sa-east-1","priceModel":"onDemand","vcpu":4,"memory":30.5,"unit":"Hrs","pricePerUnit":{"USD":"0.7000000000","CNY":""}},{"instanceType":"m5.16xlarge","region":"sa-east-1","priceModel":"onDemand","vcpu":64,"memory":256,"unit":"Hrs","pricePerUnit":{"USD":"4.8960000000","CNY":""}},{"instanceType":"c6in.8xlarge","region":"sa-east-1","priceModel":"onDemand","vcpu":32,"memory":64,"unit":"Hrs","pricePerUnit":{"USD":"2.7888000000","CNY":""}},{"instanceType":"t3a.large","region":"sa-east-1","priceModel":"onDemand","vcpu":2,"memory":8,"unit":"Hrs","pricePerUnit":{"USD":"0.1210000000","CNY":""}},{"instanceType":"c6in.4xlarge","region":"sa-east-1","priceModel":"onDemand","vcpu":16,"memory":32,"unit":"Hrs","pricePerUnit":{"USD":"1.3944000000","CNY":""}},{"instanceType":"m5d.2xlarge","region":"sa-east-1","priceModel":"onDemand","vcpu":8,"memory":32,"unit":"Hrs","pricePerUnit":{"USD":"0.7200000000","CNY":""}},{"instanceType":"r5b.24xlarge","region":"sa-east-1","priceModel":"onDemand","vcpu":96,"memory":768,"unit":"Hrs","pricePerUnit":{"USD":"11.3760000000","CNY":""}},{"instanceType":"m1.large","region":"sa-east-1","priceModel":"onDemand","vcpu":2,"memory":7.5,"unit":"Hrs","pricePerUnit":{"USD":"0.2330000000","CNY":""}},{"instanceType":"m3.2xlarge","region":"sa-east-1","priceModel":"onDemand","vcpu":8,"memory":30,"unit":"Hrs","pricePerUnit":{"USD":"0.7610000000","CNY":""}},{"instanceType":"m6gd.xlarge","region":"sa-east-1","priceModel":"onDemand","vcpu":4,"memory":16,"unit":"Hrs","pricePerUnit":{"USD":"0.2880000000","CNY":""}},{"instanceType":"t3.xlarge","region":"sa-east-1","priceModel":"onDemand","vcpu":4,"memory":16,"unit":"Hrs","pricePerUnit":{"USD":"0.2688000000","CNY":""}},{"instanceType":"c6gd.medium","region":"sa-east-1","priceModel":"onDemand","vcpu":1,"memory":2,"unit":"Hrs","pricePerUnit":{"USD":"0.0595000000","CNY":""}},{"instanceType":"m5d.large","region":"sa-east-1","priceModel":"onDemand","vcpu":2,"memory":8,"unit":"Hrs","pricePerUnit":{"USD":"0.1800000000","CNY":""}},{"instanceType":"m5d.16xlarge","region":"sa-east-1","priceModel":"onDemand","vcpu":64,"memory":256,"unit":"Hrs","pricePerUnit":{"USD":"5.7600000000","CNY":""}},{"instanceType":"c5.4xlarge","region":"sa-east-1","priceModel":"onDemand","vcpu":16,"memory":32,"unit":"Hrs","pricePerUnit":{"USD":"1.0480000000","CNY":""}},{"instanceType":"r5.large","region":"sa-east-1","priceModel":"onDemand","vcpu":2,"memory":16,"unit":"Hrs","pricePerUnit":{"USD":"0.2010000000","CNY":""}},{"instanceType":"t3a.2xlarge","region":"sa-east-1","priceModel":"onDemand","vcpu":8,"memory":32,"unit":"Hrs","pricePerUnit":{"USD":"0.4838000000","CNY":""}},{"instanceType":"r6gd.16xlarge","region":"sa-east-1","priceModel":"onDemand","vcpu":64,"memory":512,"unit":"Hrs","pricePerUnit":{"USD":"5.8368000000","CNY":""}},{"instanceType":"m5ad.large","region":"sa-east-1","priceModel":"onDemand","vcpu":2,"memory":8,"unit":"Hrs","pricePerUnit":{"USD":"0.1650000000","CNY":""}},{"instanceType":"t2.micro","region":"sa-east-1","priceModel":"onDemand","vcpu":1,"memory":1,"unit":"Hrs","pricePerUnit":{"USD":"0.0186000000","CNY":""}},{"instanceType":"c6i.8xlarge","region":"sa-east-1","priceModel":"onDemand","vcpu":32,"memory":64,"unit":"Hrs","pricePerUnit":{"USD":"2.0960000000","CNY":""}},{"instanceType":"c6g.medium","region":"sa-east-1","priceModel":"onDemand","vcpu":1,"memory":2,"unit":"Hrs","pricePerUnit":{"USD":"0.0524000000","CNY":""}},{"instanceType":"m5zn.metal","region":"sa-east-1","priceModel":"onDemand","vcpu":48,"memory":192,"unit":"Hrs","pricePerUnit":{"USD":"6.3178000000","CNY":""}},{"instanceType":"c6i.large","region":"sa-east-1","priceModel":"onDemand","vcpu":2,"memory":4,"unit":"Hrs","pricePerUnit":{"USD":"0.1310000000","CNY":""}},{"instanceType":"r5a.xlarge","region":"sa-east-1","priceModel":"onDemand","vcpu":4,"memory":32,"unit":"Hrs","pricePerUnit":{"USD":"0.3620000000","CNY":""}},{"instanceType":"i3en.xlarge","region":"sa-east-1","priceModel":"onDemand","vcpu":4,"memory":32,"unit":"Hrs","pricePerUnit":{"USD":"0.7200000000","CNY":""}},{"instanceType":"c5d.24xlarge","region":"sa-east-1","priceModel":"onDemand","vcpu":96,"memory":192,"unit":"Hrs","pricePerUnit":{"USD":"7.1520000000","CNY":""}},{"instanceType":"r3.2xlarge","region":"sa-east-1","priceModel":"onDemand","vcpu":8,"memory":61,"unit":"Hrs","pricePerUnit":{"USD":"1.3990000000","CNY":""}},{"instanceType":"t1.micro","region":"sa-east-1","priceModel":"onDemand","vcpu":1,"memory":0.613,"unit":"Hrs","pricePerUnit":{"USD":"0.0270000000","CNY":""}},{"instanceType":"m6gd.16xlarge","region":"sa-east-1","priceModel":"onDemand","vcpu":64,"memory":256,"unit":"Hrs","pricePerUnit":{"USD":"4.6080000000","CNY":""}},{"instanceType":"c5d.12xlarge","region":"sa-east-1","priceModel":"onDemand","vcpu":48,"memory":96,"unit":"Hrs","pricePerUnit":{"USD":"3.5760000000","CNY":""}},{"instanceType":"i4i.32xlarge","region":"sa-east-1","priceModel":"onDemand","vcpu":128,"memory":1024,"unit":"Hrs","pricePerUnit":{"USD":"17.5296000000","CNY":""}},{"instanceType":"r6gd.4xlarge","region":"sa-east-1","priceModel":"onDemand","vcpu":16,"memory":128,"unit":"Hrs","pricePerUnit":{"USD":"1.4592000000","CNY":""}},{"instanceType":"m5a.2xlarge","region":"sa-east-1","priceModel":"onDemand","vcpu":8,"memory":32,"unit":"Hrs","pricePerUnit":{"USD":"0.5520000000","CNY":""}},{"instanceType":"x2iedn.xlarge","region":"sa-east-1","priceModel":"onDemand","vcpu":4,"memory":128,"unit":"Hrs","pricePerUnit":{"USD":"1.6256300000","CNY":""}},{"instanceType":"i4i.large","region":"sa-east-1","priceModel":"onDemand","vcpu":2,"memory":16,"unit":"Hrs","pricePerUnit":{"USD":"0.2740000000","CNY":""}},{"instanceType":"i4i.16xlarge","region":"sa-east-1","priceModel":"onDemand","vcpu":64,"memory":512,"unit":"Hrs","pricePerUnit":{"USD":"8.7650000000","CNY":""}},{"instanceType":"r5d.large","region":"sa-east-1","priceModel":"onDemand","vcpu":2,"memory":16,"unit":"Hrs","pricePerUnit":{"USD":"0.2280000000","CNY":""}},{"instanceType":"m5d.8xlarge","region":"sa-east-1","priceModel":"onDemand","vcpu":32,"memory":128,"unit":"Hrs","pricePerUnit":{"USD":"2.8800000000","CNY":""}},{"instanceType":"c6a.8xlarge","region":"sa-east-1","priceModel":"onDemand","vcpu":32,"memory":64,"unit":"Hrs","pricePerUnit":{"USD":"1.8864000000","CNY":""}},{"instanceType":"t3.nano","region":"sa-east-1","priceModel":"onDemand","vcpu":2,"memory":0.5,"unit":"Hrs","pricePerUnit":{"USD":"0.0084000000","CNY":""}},{"instanceType":"r5a.large","region":"sa-east-1","priceModel":"onDemand","vcpu":2,"memory":16,"unit":"Hrs","pricePerUnit":{"USD":"0.1810000000","CNY":""}},{"instanceType":"g4dn.8xlarge","region":"sa-east-1","priceModel":"onDemand","vcpu":32,"memory":128,"unit":"Hrs","pricePerUnit":{"USD":"3.6980000000","CNY":""}},{"instanceType":"c6in.16xlarge","region":"sa-east-1","priceModel":"onDemand","vcpu":64,"memory":128,"unit":"Hrs","pricePerUnit":{"USD":"5.5776000000","CNY":""}},{"instanceType":"m6i.large","region":"sa-east-1","priceModel":"onDemand","vcpu":2,"memory":8,"unit":"Hrs","pricePerUnit":{"USD":"0.1530000000","CNY":""}},{"instanceType":"r5.24xlarge","region":"sa-east-1","priceModel":"onDemand","vcpu":96,"memory":768,"unit":"Hrs","pricePerUnit":{"USD":"9.6480000000","CNY":""}},{"instanceType":"c5n.large","region":"sa-east-1","priceModel":"onDemand","vcpu":2,"memory":5.25,"unit":"Hrs","pricePerUnit":{"USD":"0.1660000000","CNY":""}},{"instanceType":"m6a.12xlarge","region":"sa-east-1","priceModel":"onDemand","vcpu":48,"memory":192,"unit":"Hrs","pricePerUnit":{"USD":"3.3048000000","CNY":""}},{"instanceType":"c6g.8xlarge","region":"sa-east-1","priceModel":"onDemand","vcpu":32,"memory":64,"unit":"Hrs","pricePerUnit":{"USD":"1.6768000000","CNY":""}},{"instanceType":"r5ad.4xlarge","region":"sa-east-1","priceModel":"onDemand","vcpu":16,"memory":128,"unit":"Hrs","pricePerUnit":{"USD":"1.6640000000","CNY":""}},{"instanceType":"t4g.2xlarge","region":"sa-east-1","priceModel":"onDemand","vcpu":8,"memory":32,"unit":"Hrs","pricePerUnit":{"USD":"0.4288000000","CNY":""}},{"instanceType":"m5d.xlarge","region":"sa-east-1","priceModel":"onDemand","vcpu":4,"memory":16,"unit":"Hrs","pricePerUnit":{"USD":"0.3600000000","CNY":""}},{"instanceType":"t4g.nano","region":"sa-east-1","priceModel":"onDemand","vcpu":2,"memory":0.5,"unit":"Hrs","pricePerUnit":{"USD":"0.0067000000","CNY":""}},{"instanceType":"t3.small","region":"sa-east-1","priceModel":"onDemand","vcpu":2,"memory":2,"unit":"Hrs","pricePerUnit":{"USD":"0.0336000000","CNY":""}},{"instanceType":"c1.medium","region":"sa-east-1","priceModel":"onDemand","vcpu":2,"memory":1.7,"unit":"Hrs","pricePerUnit":{"USD":"0.1790000000","CNY":""}},{"instanceType":"r4.xlarge","region":"sa-east-1","priceModel":"onDemand","vcpu":4,"memory":30.5,"unit":"Hrs","pricePerUnit":{"USD":"0.5600000000","CNY":""}},{"instanceType":"c5ad.16xlarge","region":"sa-east-1","priceModel":"onDemand","vcpu":64,"memory":128,"unit":"Hrs","pricePerUnit":{"USD":"4.2880000000","CNY":""}},{"instanceType":"m5a.8xlarge","region":"sa-east-1","priceModel":"onDemand","vcpu":32,"memory":128,"unit":"Hrs","pricePerUnit":{"USD":"2.2080000000","CNY":""}},{"instanceType":"x2iedn.24xlarge","region":"sa-east-1","priceModel":"onDemand","vcpu":96,"memory":3072,"unit":"Hrs","pricePerUnit":{"USD":"39.0150000000","CNY":""}},{"instanceType":"g4dn.2xlarge","region":"sa-east-1","priceModel":"onDemand","vcpu":8,"memory":32,"unit":"Hrs","pricePerUnit":{"USD":"1.2780000000","CNY":""}},{"instanceType":"c5d.18xlarge","region":"sa-east-1","priceModel":"onDemand","vcpu":72,"memory":144,"unit":"Hrs","pricePerUnit":{"USD":"5.3640000000","CNY":""}},{"instanceType":"x1e.32xlarge","region":"sa-east-1","priceModel":"onDemand","vcpu":128,"memory":3904,"unit":"Hrs","pricePerUnit":{"USD":"52.0190000000","CNY":""}},{"instanceType":"x1e.4xlarge","region":"sa-east-1","priceModel":"onDemand","vcpu":16,"memory":488,"unit":"Hrs","pricePerUnit":{"USD":"6.5020000000","CNY":""}},{"instanceType":"g4dn.12xlarge","region":"sa-east-1","priceModel":"onDemand","vcpu":48,"memory":192,"unit":"Hrs","pricePerUnit":{"USD":"6.6490000000","CNY":""}},{"instanceType":"m5a.large","region":"sa-east-1","priceModel":"onDemand","vcpu":2,"memory":8,"unit":"Hrs","pricePerUnit":{"USD":"0.1380000000","CNY":""}},{"instanceType":"i3.2xlarge","region":"sa-east-1","priceModel":"onDemand","vcpu":8,"memory":61,"unit":"Hrs","pricePerUnit":{"USD":"0.9960000000","CNY":""}},{"instanceType":"c5d.4xlarge","region":"sa-east-1","priceModel":"onDemand","vcpu":16,"memory":32,"unit":"Hrs","pricePerUnit":{"USD":"1.1920000000","CNY":""}},{"instanceType":"m5d.metal","region":"sa-east-1","priceModel":"onDemand","vcpu":96,"memory":384,"unit":"Hrs","pricePerUnit":{"USD":"8.6400000000","CNY":""}},{"instanceType":"m6i.24xlarge","region":"sa-east-1","priceModel":"onDemand","vcpu":96,"memory":384,"unit":"Hrs","pricePerUnit":{"USD":"7.3440000000","CNY":""}},{"instanceType":"m6i.xlarge","region":"sa-east-1","priceModel":"onDemand","vcpu":4,"memory":16,"unit":"Hrs","pricePerUnit":{"USD":"0.3060000000","CNY":""}},{"instanceType":"r6g.16xlarge","region":"sa-east-1","priceModel":"onDemand","vcpu":64,"memory":512,"unit":"Hrs","pricePerUnit":{"USD":"5.1456000000","CNY":""}},{"instanceType":"r3.4xlarge","region":"sa-east-1","priceModel":"onDemand","vcpu":16,"memory":122,"unit":"Hrs","pricePerUnit":{"USD":"2.7990000000","CNY":""}},{"instanceType":"x2idn.metal","region":"sa-east-1","priceModel":"onDemand","vcpu":128,"memory":2048,"unit":"Hrs","pricePerUnit":{"USD":"26.0100000000","CNY":""}},{"instanceType":"r6i.xlarge","region":"sa-east-1","priceModel":"onDemand","vcpu":4,"memory":32,"unit":"Hrs","pricePerUnit":{"USD":"0.4020000000","CNY":""}},{"instanceType":"m6gd.large","region":"sa-east-1","priceModel":"onDemand","vcpu":2,"memory":8,"unit":"Hrs","pricePerUnit":{"USD":"0.1440000000","CNY":""}},{"instanceType":"m6a.32xlarge","region":"sa-east-1","priceModel":"onDemand","vcpu":128,"memory":512,"unit":"Hrs","pricePerUnit":{"USD":"8.8128000000","CNY":""}},{"instanceType":"r5ad.12xlarge","region":"sa-east-1","priceModel":"onDemand","vcpu":48,"memory":384,"unit":"Hrs","pricePerUnit":{"USD":"4.9920000000","CNY":""}},{"instanceType":"r6g.metal","region":"sa-east-1","priceModel":"onDemand","vcpu":64,"memory":512,"unit":"Hrs","pricePerUnit":{"USD":"5.1456000000","CNY":""}},{"instanceType":"t4g.medium","region":"sa-east-1","priceModel":"onDemand","vcpu":2,"memory":4,"unit":"Hrs","pricePerUnit":{"USD":"0.0536000000","CNY":""}},{"instanceType":"c5.24xlarge","region":"sa-east-1","priceModel":"onDemand","vcpu":96,"memory":192,"unit":"Hrs","pricePerUnit":{"USD":"6.2880000000","CNY":""}},{"instanceType":"m3.large","region":"sa-east-1","priceModel":"onDemand","vcpu":2,"memory":7.5,"unit":"Hrs","pricePerUnit":{"USD":"0.1900000000","CNY":""}},{"instanceType":"x2idn.16xlarge","region":"sa-east-1","priceModel":"onDemand","vcpu":64,"memory":1024,"unit":"Hrs","pricePerUnit":{"USD":"13.0050000000","CNY":""}},{"instanceType":"r4.16xlarge","region":"sa-east-1","priceModel":"onDemand","vcpu":64,"memory":488,"unit":"Hrs","pricePerUnit":{"USD":"8.9600000000","CNY":""}},{"instanceType":"c6in.xlarge","region":"sa-east-1","priceModel":"onDemand","vcpu":4,"memory":8,"unit":"Hrs","pricePerUnit":{"USD":"0.3486000000","CNY":""}},{"instanceType":"c6i.2xlarge","region":"sa-east-1","priceModel":"onDemand","vcpu":8,"memory":16,"unit":"Hrs","pricePerUnit":{"USD":"0.5240000000","CNY":""}},{"instanceType":"c6gn.medium","region":"sa-east-1","priceModel":"onDemand","vcpu":1,"memory":2,"unit":"Hrs","pricePerUnit":{"USD":"0.0665000000","CNY":""}},{"instanceType":"g5.16xlarge","region":"sa-east-1","priceModel":"onDemand","vcpu":64,"memory":256,"unit":"Hrs","pricePerUnit":{"USD":"6.9623900000","CNY":""}},{"instanceType":"c5.xlarge","region":"sa-east-1","priceModel":"onDemand","vcpu":4,"memory":8,"unit":"Hrs","pricePerUnit":{"USD":"0.2620000000","CNY":""}},{"instanceType":"c6gn.4xlarge","region":"sa-east-1","priceModel":"onDemand","vcpu":16,"memory":32,"unit":"Hrs","pricePerUnit":{"USD":"1.0640000000","CNY":""}},{"instanceType":"m5zn.6xlarge","region":"sa-east-1","priceModel":"onDemand","vcpu":24,"memory":96,"unit":"Hrs","pricePerUnit":{"USD":"3.1589000000","CNY":""}},{"instanceType":"c6i.32xlarge","region":"sa-east-1","priceModel":"onDemand","vcpu":128,"memory":256,"unit":"Hrs","pricePerUnit":{"USD":"8.3840000000","CNY":""}},{"instanceType":"c6gd.xlarge","region":"sa-east-1","priceModel":"onDemand","vcpu":4,"memory":8,"unit":"Hrs","pricePerUnit":{"USD":"0.2380000000","CNY":""}},{"instanceType":"c5.9xlarge","region":"sa-east-1","priceModel":"onDemand","vcpu":36,"memory":72,"unit":"Hrs","pricePerUnit":{"USD":"2.3580000000","CNY":""}},{"instanceType":"g5.4xlarge","region":"sa-east-1","priceModel":"onDemand","vcpu":16,"memory":64,"unit":"Hrs","pricePerUnit":{"USD":"2.7604800000","CNY":""}},{"instanceType":"g4dn.4xlarge","region":"sa-east-1","priceModel":"onDemand","vcpu":16,"memory":64,"unit":"Hrs","pricePerUnit":{"USD":"2.0460000000","CNY":""}},{"instanceType":"t3.medium","region":"sa-east-1","priceModel":"onDemand","vcpu":2,"memory":4,"unit":"Hrs","pricePerUnit":{"USD":"0.0672000000","CNY":""}},{"instanceType":"x2iedn.2xlarge","region":"sa-east-1","priceModel":"onDemand","vcpu":8,"memory":256,"unit":"Hrs","pricePerUnit":{"USD":"3.2512500000","CNY":""}},{"instanceType":"m5.large","region":"sa-east-1","priceModel":"onDemand","vcpu":2,"memory":8,"unit":"Hrs","pricePerUnit":{"USD":"0.1530000000","CNY":""}},{"instanceType":"m5.24xlarge","region":"sa-east-1","priceModel":"onDemand","vcpu":96,"memory":384,"unit":"Hrs","pricePerUnit":{"USD":"7.3440000000","CNY":""}},{"instanceType":"r5n.24xlarge","region":"sa-east-1","priceModel":"onDemand","vcpu":96,"memory":768,"unit":"Hrs","pricePerUnit":{"USD":"11.3280000000","CNY":""}},{"instanceType":"c6gd.4xlarge","region":"sa-east-1","priceModel":"onDemand","vcpu":16,"memory":32,"unit":"Hrs","pricePerUnit":{"USD":"0.9520000000","CNY":""}},{"instanceType":"m5d.4xlarge","region":"sa-east-1","priceModel":"onDemand","vcpu":16,"memory":64,"unit":"Hrs","pricePerUnit":{"USD":"1.4400000000","CNY":""}},{"instanceType":"t3a.small","region":"sa-east-1","priceModel":"onDemand","vcpu":2,"memory":2,"unit":"Hrs","pricePerUnit":{"USD":"0.0302000000","CNY":""}},{"instanceType":"r5b.4xlarge","region":"sa-east-1","priceModel":"onDemand","vcpu":16,"memory":128,"unit":"Hrs","pricePerUnit":{"USD":"1.8960000000","CNY":""}},{"instanceType":"m6i.12xlarge","region":"sa-east-1","priceModel":"onDemand","vcpu":48,"memory":192,"unit":"Hrs","pricePerUnit":{"USD":"3.6720000000","CNY":""}},{"instanceType":"m6a.xlarge","region":"sa-east-1","priceModel":"onDemand","vcpu":4,"memory":16,"unit":"Hrs","pricePerUnit":{"USD":"0.2754000000","CNY":""}},{"instanceType":"r5.2xlarge","region":"sa-east-1","priceModel":"onDemand","vcpu":8,"memory":64,"unit":"Hrs","pricePerUnit":{"USD":"0.8040000000","CNY":""}},{"instanceType":"r5ad.large","region":"sa-east-1","priceModel":"onDemand","vcpu":2,"memory":16,"unit":"Hrs","pricePerUnit":{"USD":"0.2080000000","CNY":""}},{"instanceType":"c5d.large","region":"sa-east-1","priceModel":"onDemand","vcpu":2,"memory":4,"unit":"Hrs","pricePerUnit":{"USD":"0.1490000000","CNY":""}},{"instanceType":"x1e.xlarge","region":"sa-east-1","priceModel":"onDemand","vcpu":4,"memory":122,"unit":"Hrs","pricePerUnit":{"USD":"1.6260000000","CNY":""}},{"instanceType":"c4.2xlarge","region":"sa-east-1","priceModel":"onDemand","vcpu":8,"memory":15,"unit":"Hrs","pricePerUnit":{"USD":"0.6180000000","CNY":""}},{"instanceType":"c3.xlarge","region":"sa-east-1","priceModel":"onDemand","vcpu":4,"memory":7.5,"unit":"Hrs","pricePerUnit":{"USD":"0.3250000000","CNY":""}},{"instanceType":"m5.xlarge","region":"sa-east-1","priceModel":"onDemand","vcpu":4,"memory":16,"unit":"Hrs","pricePerUnit":{"USD":"0.3060000000","CNY":""}},{"instanceType":"x2idn.24xlarge","region":"sa-east-1","priceModel":"onDemand","vcpu":96,"memory":1536,"unit":"Hrs","pricePerUnit":{"USD":"19.5075000000","CNY":""}},{"instanceType":"g4dn.xlarge","region":"sa-east-1","priceModel":"onDemand","vcpu":4,"memory":16,"unit":"Hrs","pricePerUnit":{"USD":"0.8940000000","CNY":""}},{"instanceType":"r5ad.xlarge","region":"sa-east-1","priceModel":"onDemand","vcpu":4,"memory":32,"unit":"Hrs","pricePerUnit":{"USD":"0.4160000000","CNY":""}},{"instanceType":"m6g.4xlarge","region":"sa-east-1","priceModel":"onDemand","vcpu":16,"memory":64,"unit":"Hrs","pricePerUnit":{"USD":"0.9792000000","CNY":""}},{"instanceType":"inf1.2xlarge","region":"sa-east-1","priceModel":"onDemand","vcpu":8,"memory":16,"unit":"Hrs","pricePerUnit":{"USD":"0.5980000000","CNY":""}},{"instanceType":"c6in.12xlarge","region":"sa-east-1","priceModel":"onDemand","vcpu":48,"memory":96,"unit":"Hrs","pricePerUnit":{"USD":"4.1832000000","CNY":""}},{"instanceType":"c5a.2xlarge","region":"sa-east-1","priceModel":"onDemand","vcpu":8,"memory":16,"unit":"Hrs","pricePerUnit":{"USD":"0.4720000000","CNY":""}},{"instanceType":"r5a.24xlarge","region":"sa-east-1","priceModel":"onDemand","vcpu":96,"memory":768,"unit":"Hrs","pricePerUnit":{"USD":"8.6880000000","CNY":""}},{"instanceType":"m3.medium","region":"sa-east-1","priceModel":"onDemand","vcpu":1,"memory":3.75,"unit":"Hrs","pricePerUnit":{"USD":"0.0950000000","CNY":""}},{"instanceType":"g5.xlarge","region":"sa-east-1","priceModel":"onDemand","vcpu":4,"memory":16,"unit":"Hrs","pricePerUnit":{"USD":"1.7100000000","CNY":""}},{"instanceType":"r4.8xlarge","region":"sa-east-1","priceModel":"onDemand","vcpu":32,"memory":244,"unit":"Hrs","pricePerUnit":{"USD":"4.4800000000","CNY":""}},{"instanceType":"r5ad.24xlarge","region":"sa-east-1","priceModel":"onDemand","vcpu":96,"memory":768,"unit":"Hrs","pricePerUnit":{"USD":"9.9840000000","CNY":""}},{"instanceType":"c6in.2xlarge","region":"sa-east-1","priceModel":"onDemand","vcpu":8,"memory":16,"unit":"Hrs","pricePerUnit":{"USD":"0.6972000000","CNY":""}},{"instanceType":"i3en.large","region":"sa-east-1","priceModel":"onDemand","vcpu":2,"memory":16,"unit":"Hrs","pricePerUnit":{"USD":"0.3600000000","CNY":""}},{"instanceType":"m6g.xlarge","region":"sa-east-1","priceModel":"onDemand","vcpu":4,"memory":16,"unit":"Hrs","pricePerUnit":{"USD":"0.2448000000","CNY":""}},{"instanceType":"t4g.large","region":"sa-east-1","priceModel":"onDemand","vcpu":2,"memory":8,"unit":"Hrs","pricePerUnit":{"USD":"0.1072000000","CNY":""}},{"instanceType":"c5a.large","region":"sa-east-1","priceModel":"onDemand","vcpu":2,"memory":4,"unit":"Hrs","pricePerUnit":{"USD":"0.1180000000","CNY":""}},{"instanceType":"r5ad.16xlarge","region":"sa-east-1","priceModel":"onDemand","vcpu":64,"memory":512,"unit":"Hrs","pricePerUnit":{"USD":"6.6560000000","CNY":""}},{"instanceType":"m6gd.8xlarge","region":"sa-east-1","priceModel":"onDemand","vcpu":32,"memory":128,"unit":"Hrs","pricePerUnit":{"USD":"2.3040000000","CNY":""}},{"instanceType":"m1.xlarge","region":"sa-east-1","priceModel":"onDemand","vcpu":4,"memory":15,"unit":"Hrs","pricePerUnit":{"USD":"0.4670000000","CNY":""}},{"instanceType":"c6gd.12xlarge","region":"sa-east-1","priceModel":"onDemand","vcpu":48,"memory":96,"unit":"Hrs","pricePerUnit":{"USD":"2.8560000000","CNY":""}},{"instanceType":"r5n.16xlarge","region":"sa-east-1","priceModel":"onDemand","vcpu":64,"memory":512,"unit":"Hrs","pricePerUnit":{"USD":"7.5520000000","CNY":""}},{"instanceType":"r5b.xlarge","region":"sa-east-1","priceModel":"onDemand","vcpu":4,"memory":32,"unit":"Hrs","pricePerUnit":{"USD":"0.4740000000","CNY":""}},{"instanceType":"c5a.4xlarge","region":"sa-east-1","priceModel":"onDemand","vcpu":16,"memory":32,"unit":"Hrs","pricePerUnit":{"USD":"0.9440000000","CNY":""}},{"instanceType":"c5n.xlarge","region":"sa-east-1","priceModel":"onDemand","vcpu":4,"memory":10.5,"unit":"Hrs","pricePerUnit":{"USD":"0.3320000000","CNY":""}},{"instanceType":"c6in.large","region":"sa-east-1","priceModel":"onDemand","vcpu":2,"memory":4,"unit":"Hrs","pricePerUnit":{"USD":"0.1743000000","CNY":""}},{"instanceType":"m4.2xlarge","region":"sa-east-1","priceModel":"onDemand","vcpu":8,"memory":32,"unit":"Hrs","pricePerUnit":{"USD":"0.6360000000","CNY":""}},{"instanceType":"c5.12xlarge","region":"sa-east-1","priceModel":"onDemand","vcpu":48,"memory":96,"unit":"Hrs","pricePerUnit":{"USD":"3.1440000000","CNY":""}},{"instanceType":"m6i.8xlarge","region":"sa-east-1","priceModel":"onDemand","vcpu":32,"memory":128,"unit":"Hrs","pricePerUnit":{"USD":"2.4480000000","CNY":""}},{"instanceType":"inf1.24xlarge","region":"sa-east-1","priceModel":"onDemand","vcpu":96,"memory":192,"unit":"Hrs","pricePerUnit":{"USD":"7.8000000000","CNY":""}},{"instanceType":"x1e.8xlarge","region":"sa-east-1","priceModel":"onDemand","vcpu":32,"memory":976,"unit":"Hrs","pricePerUnit":{"USD":"13.0050000000","CNY":""}},{"instanceType":"c6a.24xlarge","region":"sa-east-1","priceModel":"onDemand","vcpu":96,"memory":192,"unit":"Hrs","pricePerUnit":{"USD":"5.6592000000","CNY":""}},{"instanceType":"m5ad.12xlarge","region":"sa-east-1","priceModel":"onDemand","vcpu":48,"memory":192,"unit":"Hrs","pricePerUnit":{"USD":"3.9600000000","CNY":""}},{"instanceType":"r6gd.12xlarge","region":"sa-east-1","priceModel":"onDemand","vcpu":48,"memory":384,"unit":"Hrs","pricePerUnit":{"USD":"4.3776000000","CNY":""}},{"instanceType":"i3en.2xlarge","region":"sa-east-1","priceModel":"onDemand","vcpu":8,"memory":64,"unit":"Hrs","pricePerUnit":{"USD":"1.4400000000","CNY":""}},{"instanceType":"m5zn.3xlarge","region":"sa-east-1","priceModel":"onDemand","vcpu":12,"memory":48,"unit":"Hrs","pricePerUnit":{"USD":"1.5794000000","CNY":""}},{"instanceType":"g5.2xlarge","region":"sa-east-1","priceModel":"onDemand","vcpu":8,"memory":32,"unit":"Hrs","pricePerUnit":{"USD":"2.0601600000","CNY":""}},{"instanceType":"r5b.large","region":"sa-east-1","priceModel":"onDemand","vcpu":2,"memory":16,"unit":"Hrs","pricePerUnit":{"USD":"0.2370000000","CNY":""}},{"instanceType":"x2iedn.4xlarge","region":"sa-east-1","priceModel":"onDemand","vcpu":16,"memory":512,"unit":"Hrs","pricePerUnit":{"USD":"6.5025000000","CNY":""}},{"instanceType":"m4.large","region":"sa-east-1","priceModel":"onDemand","vcpu":2,"memory":8,"unit":"Hrs","pricePerUnit":{"USD":"0.1590000000","CNY":""}},{"instanceType":"c5ad.4xlarge","region":"sa-east-1","priceModel":"onDemand","vcpu":16,"memory":32,"unit":"Hrs","pricePerUnit":{"USD":"1.0720000000","CNY":""}},{"instanceType":"i3en.24xlarge","region":"sa-east-1","priceModel":"onDemand","vcpu":96,"memory":768,"unit":"Hrs","pricePerUnit":{"USD":"17.2800000000","CNY":""}},{"instanceType":"t3a.medium","region":"sa-east-1","priceModel":"onDemand","vcpu":2,"memory":4,"unit":"Hrs","pricePerUnit":{"USD":"0.0605000000","CNY":""}},{"instanceType":"r6g.large","region":"sa-east-1","priceModel":"onDemand","vcpu":2,"memory":16,"unit":"Hrs","pricePerUnit":{"USD":"0.1608000000","CNY":""}},{"instanceType":"r6g.4xlarge","region":"sa-east-1","priceModel":"onDemand","vcpu":16,"memory":128,"unit":"Hrs","pricePerUnit":{"USD":"1.2864000000","CNY":""}},{"instanceType":"m6i.4xlarge","region":"sa-east-1","priceModel":"onDemand","vcpu":16,"memory":64,"unit":"Hrs","pricePerUnit":{"USD":"1.2240000000","CNY":""}},{"instanceType":"m5a.4xlarge","region":"sa-east-1","priceModel":"onDemand","vcpu":16,"memory":64,"unit":"Hrs","pricePerUnit":{"USD":"1.1040000000","CNY":""}},{"instanceType":"m6a.48xlarge","region":"sa-east-1","priceModel":"onDemand","vcpu":192,"memory":768,"unit":"Hrs","pricePerUnit":{"USD":"13.2192000000","CNY":""}},{"instanceType":"t3.large","region":"sa-east-1","priceModel":"onDemand","vcpu":2,"memory":8,"unit":"Hrs","pricePerUnit":{"USD":"0.1344000000","CNY":""}},{"instanceType":"m6i.32xlarge","region":"sa-east-1","priceModel":"onDemand","vcpu":128,"memory":512,"unit":"Hrs","pricePerUnit":{"USD":"9.7920000000","CNY":""}},{"instanceType":"c6gn.large","region":"sa-east-1","priceModel":"onDemand","vcpu":2,"memory":4,"unit":"Hrs","pricePerUnit":{"USD":"0.1330000000","CNY":""}},{"instanceType":"m5d.24xlarge","region":"sa-east-1","priceModel":"onDemand","vcpu":96,"memory":384,"unit":"Hrs","pricePerUnit":{"USD":"8.6400000000","CNY":""}},{"instanceType":"c5a.24xlarge","region":"sa-east-1","priceModel":"onDemand","vcpu":96,"memory":192,"unit":"Hrs","pricePerUnit":{"USD":"5.6640000000","CNY":""}},{"instanceType":"m3.xlarge","region":"sa-east-1","priceModel":"onDemand","vcpu":4,"memory":15,"unit":"Hrs","pricePerUnit":{"USD":"0.3810000000","CNY":""}},{"instanceType":"r5a.4xlarge","region":"sa-east-1","priceModel":"onDemand","vcpu":16,"memory":128,"unit":"Hrs","pricePerUnit":{"USD":"1.4480000000","CNY":""}},{"instanceType":"i4i.4xlarge","region":"sa-east-1","priceModel":"onDemand","vcpu":16,"memory":128,"unit":"Hrs","pricePerUnit":{"USD":"2.1910000000","CNY":""}},{"instanceType":"c6a.32xlarge","region":"sa-east-1","priceModel":"onDemand","vcpu":128,"memory":256,"unit":"Hrs","pricePerUnit":{"USD":"7.5456000000","CNY":""}},{"instanceType":"r5ad.2xlarge","region":"sa-east-1","priceModel":"onDemand","vcpu":8,"memory":64,"unit":"Hrs","pricePerUnit":{"USD":"0.8320000000","CNY":""}},{"instanceType":"c6in.metal","region":"sa-east-1","priceModel":"onDemand","vcpu":128,"memory":256,"unit":"Hrs","pricePerUnit":{"USD":"11.1552000000","CNY":""}},{"instanceType":"m4.10xlarge","region":"sa-east-1","priceModel":"onDemand","vcpu":40,"memory":160,"unit":"Hrs","pricePerUnit":{"USD":"3.1800000000","CNY":""}},{"instanceType":"c6gn.xlarge","region":"sa-east-1","priceModel":"onDemand","vcpu":4,"memory":8,"unit":"Hrs","pricePerUnit":{"USD":"0.2660000000","CNY":""}},{"instanceType":"t3a.nano","region":"sa-east-1","priceModel":"onDemand","vcpu":2,"memory":0.5,"unit":"Hrs","pricePerUnit":{"USD":"0.0076000000","CNY":""}},{"instanceType":"x1.16xlarge","region":"sa-east-1","priceModel":"onDemand","vcpu":64,"memory":976,"unit":"Hrs","pricePerUnit":{"USD":"13.0050000000","CNY":""}},{"instanceType":"r5n.12xlarge","region":"sa-east-1","priceModel":"onDemand","vcpu":48,"memory":384,"unit":"Hrs","pricePerUnit":{"USD":"5.6640000000","CNY":""}},{"instanceType":"t4g.small","region":"sa-east-1","priceModel":"onDemand","vcpu":2,"memory":2,"unit":"Hrs","pricePerUnit":{"USD":"0.0268000000","CNY":""}},{"instanceType":"r5d.xlarge","region":"sa-east-1","priceModel":"onDemand","vcpu":4,"memory":32,"unit":"Hrs","pricePerUnit":{"USD":"0.4560000000","CNY":""}},{"instanceType":"g4dn.16xlarge","region":"sa-east-1","priceModel":"onDemand","vcpu":64,"memory":256,"unit":"Hrs","pricePerUnit":{"USD":"7.3970000000","CNY":""}},{"instanceType":"i3en.12xlarge","region":"sa-east-1","priceModel":"onDemand","vcpu":48,"memory":384,"unit":"Hrs","pricePerUnit":{"USD":"8.6400000000","CNY":""}},{"instanceType":"i3en.3xlarge","region":"sa-east-1","priceModel":"onDemand","vcpu":12,"memory":96,"unit":"Hrs","pricePerUnit":{"USD":"2.1600000000","CNY":""}},{"instanceType":"r6g.2xlarge","region":"sa-east-1","priceModel":"onDemand","vcpu":8,"memory":64,"unit":"Hrs","pricePerUnit":{"USD":"0.6432000000","CNY":""}},{"instanceType":"r4.4xlarge","region":"sa-east-1","priceModel":"onDemand","vcpu":16,"memory":122,"unit":"Hrs","pricePerUnit":{"USD":"2.2400000000","CNY":""}},{"instanceType":"m5a.24xlarge","region":"sa-east-1","priceModel":"onDemand","vcpu":96,"memory":384,"unit":"Hrs","pricePerUnit":{"USD":"6.6240000000","CNY":""}},{"instanceType":"c3.8xlarge","region":"sa-east-1","priceModel":"onDemand","vcpu":32,"memory":60,"unit":"Hrs","pricePerUnit":{"USD":"2.6000000000","CNY":""}},{"instanceType":"c6gd.large","region":"sa-east-1","priceModel":"onDemand","vcpu":2,"memory":4,"unit":"Hrs","pricePerUnit":{"USD":"0.1190000000","CNY":""}},{"instanceType":"c6g.12xlarge","region":"sa-east-1","priceModel":"onDemand","vcpu":48,"memory":96,"unit":"Hrs","pricePerUnit":{"USD":"2.5152000000","CNY":""}},{"instanceType":"c6i.16xlarge","region":"sa-east-1","priceModel":"onDemand","vcpu":64,"memory":128,"unit":"Hrs","pricePerUnit":{"USD":"4.1920000000","CNY":""}},{"instanceType":"m6a.large","region":"sa-east-1","priceModel":"onDemand","vcpu":2,"memory":8,"unit":"Hrs","pricePerUnit":{"USD":"0.1377000000","CNY":""}},{"instanceType":"x2iedn.32xlarge","region":"sa-east-1","priceModel":"onDemand","vcpu":128,"memory":4096,"unit":"Hrs","pricePerUnit":{"USD":"52.0200000000","CNY":""}},{"instanceType":"c6in.24xlarge","region":"sa-east-1","priceModel":"onDemand","vcpu":96,"memory":192,"unit":"Hrs","pricePerUnit":{"USD":"8.3664000000","CNY":""}},{"instanceType":"i3.4xlarge","region":"sa-east-1","priceModel":"onDemand","vcpu":16,"memory":122,"unit":"Hrs","pricePerUnit":{"USD":"1.9920000000","CNY":""}},{"instanceType":"i4i.2xlarge","region":"sa-east-1","priceModel":"onDemand","vcpu":8,"memory":64,"unit":"Hrs","pricePerUnit":{"USD":"1.0960000000","CNY":""}},{"instanceType":"m6g.medium","region":"sa-east-1","priceModel":"onDemand","vcpu":1,"memory":4,"unit":"Hrs","pricePerUnit":{"USD":"0.0612000000","CNY":""}},{"instanceType":"c6gd.metal","region":"sa-east-1","priceModel":"onDemand","vcpu":64,"memory":128,"unit":"Hrs","pricePerUnit":{"USD":"3.8080000000","CNY":""}},{"instanceType":"r6gd.large","region":"sa-east-1","priceModel":"onDemand","vcpu":2,"memory":16,"unit":"Hrs","pricePerUnit":{"USD":"0.1824000000","CNY":""}},{"instanceType":"x2iedn.8xlarge","region":"sa-east-1","priceModel":"onDemand","vcpu":32,"memory":1024,"unit":"Hrs","pricePerUnit":{"USD":"13.0050000000","CNY":""}},{"instanceType":"i3en.metal","region":"sa-east-1","priceModel":"onDemand","vcpu":96,"memory":768,"unit":"Hrs","pricePerUnit":{"USD":"17.2800000000","CNY":""}},{"instanceType":"m6g.12xlarge","region":"sa-east-1","priceModel":"onDemand","vcpu":48,"memory":192,"unit":"Hrs","pricePerUnit":{"USD":"2.9376000000","CNY":""}},{"instanceType":"c5n.metal","region":"sa-east-1","priceModel":"onDemand","vcpu":72,"memory":192,"unit":"Hrs","pricePerUnit":{"USD":"5.9760000000","CNY":""}},{"instanceType":"m5.2xlarge","region":"sa-east-1","priceModel":"onDemand","vcpu":8,"memory":32,"unit":"Hrs","pricePerUnit":{"USD":"0.6120000000","CNY":""}},{"instanceType":"m5zn.xlarge","region":"sa-east-1","priceModel":"onDemand","vcpu":4,"memory":16,"unit":"Hrs","pricePerUnit":{"USD":"0.5265000000","CNY":""}},{"instanceType":"m6a.8xlarge","region":"sa-east-1","priceModel":"onDemand","vcpu":32,"memory":128,"unit":"Hrs","pricePerUnit":{"USD":"2.2032000000","CNY":""}},{"instanceType":"c3.2xlarge","region":"sa-east-1","priceModel":"onDemand","vcpu":8,"memory":15,"unit":"Hrs","pricePerUnit":{"USD":"0.6500000000","CNY":""}},{"instanceType":"t3a.xlarge","region":"sa-east-1","priceModel":"onDemand","vcpu":4,"memory":16,"unit":"Hrs","pricePerUnit":{"USD":"0.2419000000","CNY":""}},{"instanceType":"r6gd.metal","region":"sa-east-1","priceModel":"onDemand","vcpu":64,"memory":512,"unit":"Hrs","pricePerUnit":{"USD":"5.8368000000","CNY":""}},{"instanceType":"m5a.xlarge","region":"sa-east-1","priceModel":"onDemand","vcpu":4,"memory":16,"unit":"Hrs","pricePerUnit":{"USD":"0.2760000000","CNY":""}},{"instanceType":"r5.xlarge","region":"sa-east-1","priceModel":"onDemand","vcpu":4,"memory":32,"unit":"Hrs","pricePerUnit":{"USD":"0.4020000000","CNY":""}},{"instanceType":"r5b.metal","region":"sa-east-1","priceModel":"onDemand","vcpu":96,"memory":768,"unit":"Hrs","pricePerUnit":{"USD":"11.3760000000","CNY":""}},{"instanceType":"t4g.xlarge","region":"sa-east-1","priceModel":"onDemand","vcpu":4,"memory":16,"unit":"Hrs","pricePerUnit":{"USD":"0.2144000000","CNY":""}},{"instanceType":"u-12tb1.112xlarge","region":"sa-east-1","priceModel":"onDemand","vcpu":448,"memory":12288,"unit":"Hrs","pricePerUnit":{"USD":"174.2000000000","CNY":""}},{"instanceType":"r5.4xlarge","region":"sa-east-1","priceModel":"onDemand","vcpu":16,"memory":128,"unit":"Hrs","pricePerUnit":{"USD":"1.6080000000","CNY":""}},{"instanceType":"r4.2xlarge","region":"sa-east-1","priceModel":"onDemand","vcpu":8,"memory":61,"unit":"Hrs","pricePerUnit":{"USD":"1.1200000000","CNY":""}},{"instanceType":"x1e.16xlarge","region":"sa-east-1","priceModel":"onDemand","vcpu":64,"memory":1952,"unit":"Hrs","pricePerUnit":{"USD":"26.0100000000","CNY":""}},{"instanceType":"m4.xlarge","region":"sa-east-1","priceModel":"onDemand","vcpu":4,"memory":16,"unit":"Hrs","pricePerUnit":{"USD":"0.3180000000","CNY":""}},{"instanceType":"r5.8xlarge","region":"sa-east-1","priceModel":"onDemand","vcpu":32,"memory":256,"unit":"Hrs","pricePerUnit":{"USD":"3.2160000000","CNY":""}},{"instanceType":"c6g.2xlarge","region":"sa-east-1","priceModel":"onDemand","vcpu":8,"memory":16,"unit":"Hrs","pricePerUnit":{"USD":"0.4192000000","CNY":""}},{"instanceType":"m5ad.xlarge","region":"sa-east-1","priceModel":"onDemand","vcpu":4,"memory":16,"unit":"Hrs","pricePerUnit":{"USD":"0.3300000000","CNY":""}},{"instanceType":"c6a.metal","region":"sa-east-1","priceModel":"onDemand","vcpu":192,"memory":384,"unit":"Hrs","pricePerUnit":{"USD":"11.3184000000","CNY":""}},{"instanceType":"inf1.xlarge","region":"sa-east-1","priceModel":"onDemand","vcpu":4,"memory":8,"unit":"Hrs","pricePerUnit":{"USD":"0.3770000000","CNY":""}},{"instanceType":"c6a.12xlarge","region":"sa-east-1","priceModel":"onDemand","vcpu":48,"memory":96,"unit":"Hrs","pricePerUnit":{"USD":"2.8296000000","CNY":""}},{"instanceType":"r6gd.xlarge","region":"sa-east-1","priceModel":"onDemand","vcpu":4,"memory":32,"unit":"Hrs","pricePerUnit":{"USD":"0.3648000000","CNY":""}},{"instanceType":"r5d.12xlarge","region":"sa-east-1","priceModel":"onDemand","vcpu":48,"memory":384,"unit":"Hrs","pricePerUnit":{"USD":"5.4720000000","CNY":""}},{"instanceType":"c1.xlarge","region":"sa-east-1","priceModel":"onDemand","vcpu":8,"memory":7,"unit":"Hrs","pricePerUnit":{"USD":"0.7180000000","CNY":""}},{"instanceType":"u-3tb1.56xlarge","region":"sa-east-1","priceModel":"onDemand","vcpu":224,"memory":3072,"unit":"Hrs","pricePerUnit":{"USD":"43.5500000000","CNY":""}},{"instanceType":"r5ad.8xlarge","region":"sa-east-1","priceModel":"onDemand","vcpu":32,"memory":256,"unit":"Hrs","pricePerUnit":{"USD":"3.3280000000","CNY":""}},{"instanceType":"r5n.2xlarge","region":"sa-east-1","priceModel":"onDemand","vcpu":8,"memory":64,"unit":"Hrs","pricePerUnit":{"USD":"0.9440000000","CNY":""}},{"instanceType":"r6i.8xlarge","region":"sa-east-1","priceModel":"onDemand","vcpu":32,"memory":256,"unit":"Hrs","pricePerUnit":{"USD":"3.2160000000","CNY":""}},{"instanceType":"r5d.metal","region":"sa-east-1","priceModel":"onDemand","vcpu":96,"memory":768,"unit":"Hrs","pricePerUnit":{"USD":"10.9440000000","CNY":""}},{"instanceType":"c5.metal","region":"sa-east-1","priceModel":"onDemand","vcpu":96,"memory":192,"unit":"Hrs","pricePerUnit":{"USD":"6.2880000000","CNY":""}},{"instanceType":"c5ad.large","region":"sa-east-1","priceModel":"onDemand","vcpu":2,"memory":4,"unit":"Hrs","pricePerUnit":{"USD":"0.1340000000","CNY":""}},{"instanceType":"c6gn.16xlarge","region":"sa-east-1","priceModel":"onDemand","vcpu":64,"memory":128,"unit":"Hrs","pricePerUnit":{"USD":"4.2560000000","CNY":""}},{"instanceType":"m5ad.4xlarge","region":"sa-east-1","priceModel":"onDemand","vcpu":16,"memory":64,"unit":"Hrs","pricePerUnit":{"USD":"1.3200000000","CNY":""}},{"instanceType":"g5.12xlarge","region":"sa-east-1","priceModel":"onDemand","vcpu":48,"memory":192,"unit":"Hrs","pricePerUnit":{"USD":"9.6412700000","CNY":""}},{"instanceType":"t2.small","region":"sa-east-1","priceModel":"onDemand","vcpu":1,"memory":2,"unit":"Hrs","pricePerUnit":{"USD":"0.0372000000","CNY":""}},{"instanceType":"c5d.2xlarge","region":"sa-east-1","priceModel":"onDemand","vcpu":8,"memory":16,"unit":"Hrs","pricePerUnit":{"USD":"0.5960000000","CNY":""}},{"instanceType":"r5n.4xlarge","region":"sa-east-1","priceModel":"onDemand","vcpu":16,"memory":128,"unit":"Hrs","pricePerUnit":{"USD":"1.8880000000","CNY":""}},{"instanceType":"r6gd.medium","region":"sa-east-1","priceModel":"onDemand","vcpu":1,"memory":8,"unit":"Hrs","pricePerUnit":{"USD":"0.0912000000","CNY":""}},{"instanceType":"r4.large","region":"sa-east-1","priceModel":"onDemand","vcpu":2,"memory":15.25,"unit":"Hrs","pricePerUnit":{"USD":"0.2800000000","CNY":""}},{"instanceType":"c6g.4xlarge","region":"sa-east-1","priceModel":"onDemand","vcpu":16,"memory":32,"unit":"Hrs","pricePerUnit":{"USD":"0.8384000000","CNY":""}},{"instanceType":"t2.nano","region":"sa-east-1","priceModel":"onDemand","vcpu":1,"memory":0.5,"unit":"Hrs","pricePerUnit":{"USD":"0.0093000000","CNY":""}},{"instanceType":"m6a.24xlarge","region":"sa-east-1","priceModel":"onDemand","vcpu":96,"memory":384,"unit":"Hrs","pricePerUnit":{"USD":"6.6096000000","CNY":""}},{"instanceType":"c6i.xlarge","region":"sa-east-1","priceModel":"onDemand","vcpu":4,"memory":8,"unit":"Hrs","pricePerUnit":{"USD":"0.2620000000","CNY":""}},{"instanceType":"r6gd.8xlarge","region":"sa-east-1","priceModel":"onDemand","vcpu":32,"memory":256,"unit":"Hrs","pricePerUnit":{"USD":"2.9184000000","CNY":""}},{"instanceType":"r5a.2xlarge","region":"sa-east-1","priceModel":"onDemand","vcpu":8,"memory":64,"unit":"Hrs","pricePerUnit":{"USD":"0.7240000000","CNY":""}},{"instanceType":"m5ad.8xlarge","region":"sa-east-1","priceModel":"onDemand","vcpu":32,"memory":128,"unit":"Hrs","pricePerUnit":{"USD":"2.6400000000","CNY":""}},{"instanceType":"m5d.12xlarge","region":"sa-east-1","priceModel":"onDemand","vcpu":48,"memory":192,"unit":"Hrs","pricePerUnit":{"USD":"4.3200000000","CNY":""}},{"instanceType":"c5ad.24xlarge","region":"sa-east-1","priceModel":"onDemand","vcpu":96,"memory":192,"unit":"Hrs","pricePerUnit":{"USD":"6.4320000000","CNY":""}},{"instanceType":"r5.16xlarge","region":"sa-east-1","priceModel":"onDemand","vcpu":64,"memory":512,"unit":"Hrs","pricePerUnit":{"USD":"6.4320000000","CNY":""}},{"instanceType":"i3.metal","region":"sa-east-1","priceModel":"onDemand","vcpu":72,"memory":512,"unit":"Hrs","pricePerUnit":{"USD":"7.9680000000","CNY":""}},{"instanceType":"r5a.12xlarge","region":"sa-east-1","priceModel":"onDemand","vcpu":48,"memory":384,"unit":"Hrs","pricePerUnit":{"USD":"4.3440000000","CNY":""}},{"instanceType":"r5.12xlarge","region":"sa-east-1","priceModel":"onDemand","vcpu":48,"memory":384,"unit":"Hrs","pricePerUnit":{"USD":"4.8240000000","CNY":""}},{"instanceType":"m5zn.2xlarge","region":"sa-east-1","priceModel":"onDemand","vcpu":8,"memory":32,"unit":"Hrs","pricePerUnit":{"USD":"1.0530000000","CNY":""}},{"instanceType":"t2.medium","region":"sa-east-1","priceModel":"onDemand","vcpu":2,"memory":4,"unit":"Hrs","pricePerUnit":{"USD":"0.0744000000","CNY":""}},{"instanceType":"m6a.16xlarge","region":"sa-east-1","priceModel":"onDemand","vcpu":64,"memory":256,"unit":"Hrs","pricePerUnit":{"USD":"4.4064000000","CNY":""}},{"instanceType":"i3en.6xlarge","region":"sa-east-1","priceModel":"onDemand","vcpu":24,"memory":192,"unit":"Hrs","pricePerUnit":{"USD":"4.3200000000","CNY":""}},{"instanceType":"r5.metal","region":"sa-east-1","priceModel":"onDemand","vcpu":96,"memory":768,"unit":"Hrs","pricePerUnit":{"USD":"9.6480000000","CNY":""}},{"instanceType":"r5n.large","region":"sa-east-1","priceModel":"onDemand","vcpu":2,"memory":16,"unit":"Hrs","pricePerUnit":{"USD":"0.2360000000","CNY":""}},{"instanceType":"c6g.xlarge","region":"sa-east-1","priceModel":"onDemand","vcpu":4,"memory":8,"unit":"Hrs","pricePerUnit":{"USD":"0.2096000000","CNY":""}},{"instanceType":"u-6tb1.112xlarge","region":"sa-east-1","priceModel":"onDemand","vcpu":448,"memory":6144,"unit":"Hrs","pricePerUnit":{"USD":"87.1000000000","CNY":""}},{"instanceType":"c5n.18xlarge","region":"sa-east-1","priceModel":"onDemand","vcpu":72,"memory":192,"unit":"Hrs","pricePerUnit":{"USD":"5.9760000000","CNY":""}},{"instanceType":"c6a.48xlarge","region":"sa-east-1","priceModel":"onDemand","vcpu":192,"memory":384,"unit":"Hrs","pricePerUnit":{"USD":"11.3184000000","CNY":""}},{"instanceType":"m6g.16xlarge","region":"sa-east-1","priceModel":"onDemand","vcpu":64,"memory":256,"unit":"Hrs","pricePerUnit":{"USD":"3.9168000000","CNY":""}},{"instanceType":"r6g.12xlarge","region":"sa-east-1","priceModel":"onDemand","vcpu":48,"memory":384,"unit":"Hrs","pricePerUnit":{"USD":"3.8592000000","CNY":""}},{"instanceType":"c6a.xlarge","region":"sa-east-1","priceModel":"onDemand","vcpu":4,"memory":8,"unit":"Hrs","pricePerUnit":{"USD":"0.2358000000","CNY":""}},{"instanceType":"t2.large","region":"sa-east-1","priceModel":"onDemand","vcpu":2,"memory":8,"unit":"Hrs","pricePerUnit":{"USD":"0.1488000000","CNY":""}},{"instanceType":"u-6tb1.56xlarge","region":"sa-east-1","priceModel":"onDemand","vcpu":224,"memory":6144,"unit":"Hrs","pricePerUnit":{"USD":"74.0252800000","CNY":""}},{"instanceType":"m5.8xlarge","region":"sa-east-1","priceModel":"onDemand","vcpu":32,"memory":128,"unit":"Hrs","pricePerUnit":{"USD":"2.4480000000","CNY":""}},{"instanceType":"g4dn.metal","region":"sa-east-1","priceModel":"onDemand","vcpu":96,"memory":384,"unit":"Hrs","pricePerUnit":{"USD":"13.2980000000","CNY":""}},{"instanceType":"c5ad.2xlarge","region":"sa-east-1","priceModel":"onDemand","vcpu":8,"memory":16,"unit":"Hrs","pricePerUnit":{"USD":"0.5360000000","CNY":""}},{"instanceType":"t4g.micro","region":"sa-east-1","priceModel":"onDemand","vcpu":2,"memory":1,"unit":"Hrs","pricePerUnit":{"USD":"0.0134000000","CNY":""}},{"instanceType":"c6i.24xlarge","region":"sa-east-1","priceModel":"onDemand","vcpu":96,"memory":192,"unit":"Hrs","pricePerUnit":{"USD":"6.2880000000","CNY":""}},{"instanceType":"i4i.xlarge","region":"sa-east-1","priceModel":"onDemand","vcpu":4,"memory":32,"unit":"Hrs","pricePerUnit":{"USD":"0.5480000000","CNY":""}},{"instanceType":"r6i.16xlarge","region":"sa-east-1","priceModel":"onDemand","vcpu":64,"memory":512,"unit":"Hrs","pricePerUnit":{"USD":"6.4320000000","CNY":""}},{"instanceType":"c6i.4xlarge","region":"sa-east-1","priceModel":"onDemand","vcpu":16,"memory":32,"unit":"Hrs","pricePerUnit":{"USD":"1.0480000000","CNY":""}},{"instanceType":"c5.2xlarge","region":"sa-east-1","priceModel":"onDemand","vcpu":8,"memory":16,"unit":"Hrs","pricePerUnit":{"USD":"0.5240000000","CNY":""}},{"instanceType":"r6i.metal","region":"sa-east-1","priceModel":"onDemand","vcpu":128,"memory":1024,"unit":"Hrs","pricePerUnit":{"USD":"12.8640000000","CNY":""}},{"instanceType":"c5d.9xlarge","region":"sa-east-1","priceModel":"onDemand","vcpu":36,"memory":72,"unit":"Hrs","pricePerUnit":{"USD":"2.6820000000","CNY":""}},{"instanceType":"r6i.32xlarge","region":"sa-east-1","priceModel":"onDemand","vcpu":128,"memory":1024,"unit":"Hrs","pricePerUnit":{"USD":"12.8640000000","CNY":""}},{"instanceType":"m6gd.medium","region":"sa-east-1","priceModel":"onDemand","vcpu":1,"memory":4,"unit":"Hrs","pricePerUnit":{"USD":"0.0720000000","CNY":""}},{"instanceType":"m5zn.12xlarge","region":"sa-east-1","priceModel":"onDemand","vcpu":48,"memory":192,"unit":"Hrs","pricePerUnit":{"USD":"6.3178000000","CNY":""}},{"instanceType":"r3.large","region":"sa-east-1","priceModel":"onDemand","vcpu":2,"memory":15.25,"unit":"Hrs","pricePerUnit":{"USD":"0.3500000000","CNY":""}},{"instanceType":"m1.medium","region":"sa-east-1","priceModel":"onDemand","vcpu":1,"memory":3.75,"unit":"Hrs","pricePerUnit":{"USD":"0.1170000000","CNY":""}},{"instanceType":"m6g.8xlarge","region":"sa-east-1","priceModel":"onDemand","vcpu":32,"memory":128,"unit":"Hrs","pricePerUnit":{"USD":"1.9584000000","CNY":""}},{"instanceType":"m2.2xlarge","region":"sa-east-1","priceModel":"onDemand","vcpu":4,"memory":34.2,"unit":"Hrs","pricePerUnit":{"USD":"0.6450000000","CNY":""}},{"instanceType":"r5n.xlarge","region":"sa-east-1","priceModel":"onDemand","vcpu":4,"memory":32,"unit":"Hrs","pricePerUnit":{"USD":"0.4720000000","CNY":""}},{"instanceType":"r6i.2xlarge","region":"sa-east-1","priceModel":"onDemand","vcpu":8,"memory":64,"unit":"Hrs","pricePerUnit":{"USD":"0.8040000000","CNY":""}},{"instanceType":"r6g.xlarge","region":"sa-east-1","priceModel":"onDemand","vcpu":4,"memory":32,"unit":"Hrs","pricePerUnit":{"USD":"0.3216000000","CNY":""}},{"instanceType":"m6a.4xlarge","region":"sa-east-1","priceModel":"onDemand","vcpu":16,"memory":64,"unit":"Hrs","pricePerUnit":{"USD":"1.1016000000","CNY":""}},{"instanceType":"c6a.2xlarge","region":"sa-east-1","priceModel":"onDemand","vcpu":8,"memory":16,"unit":"Hrs","pricePerUnit":{"USD":"0.4716000000","CNY":""}},{"instanceType":"r5b.8xlarge","region":"sa-east-1","priceModel":"onDemand","vcpu":32,"memory":256,"unit":"Hrs","pricePerUnit":{"USD":"3.7920000000","CNY":""}},{"instanceType":"r6g.medium","region":"sa-east-1","priceModel":"onDemand","vcpu":1,"memory":8,"unit":"Hrs","pricePerUnit":{"USD":"0.0804000000","CNY":""}},{"instanceType":"m6a.2xlarge","region":"sa-east-1","priceModel":"onDemand","vcpu":8,"memory":32,"unit":"Hrs","pricePerUnit":{"USD":"0.5508000000","CNY":""}},{"instanceType":"m6a.metal","region":"sa-east-1","priceModel":"onDemand","vcpu":192,"memory":768,"unit":"Hrs","pricePerUnit":{"USD":"13.2192000000","CNY":""}},{"instanceType":"c6gn.8xlarge","region":"sa-east-1","priceModel":"onDemand","vcpu":32,"memory":64,"unit":"Hrs","pricePerUnit":{"USD":"2.1280000000","CNY":""}},{"instanceType":"m5.12xlarge","region":"sa-east-1","priceModel":"onDemand","vcpu":48,"memory":192,"unit":"Hrs","pricePerUnit":{"USD":"3.6720000000","CNY":""}},{"instanceType":"m6gd.2xlarge","region":"sa-east-1","priceModel":"onDemand","vcpu":8,"memory":32,"unit":"Hrs","pricePerUnit":{"USD":"0.5760000000","CNY":""}},{"instanceType":"c6i.12xlarge","region":"sa-east-1","priceModel":"onDemand","vcpu":48,"memory":96,"unit":"Hrs","pricePerUnit":{"USD":"3.1440000000","CNY":""}},{"instanceType":"i3.16xlarge","region":"sa-east-1","priceModel":"onDemand","vcpu":64,"memory":488,"unit":"Hrs","pricePerUnit":{"USD":"7.9680000000","CNY":""}},{"instanceType":"m6g.2xlarge","region":"sa-east-1","priceModel":"onDemand","vcpu":8,"memory":32,"unit":"Hrs","pricePerUnit":{"USD":"0.4896000000","CNY":""}},{"instanceType":"c3.4xlarge","region":"sa-east-1","priceModel":"onDemand","vcpu":16,"memory":30,"unit":"Hrs","pricePerUnit":{"USD":"1.3000000000","CNY":""}},{"instanceType":"m5a.16xlarge","region":"sa-east-1","priceModel":"onDemand","vcpu":64,"memory":256,"unit":"Hrs","pricePerUnit":{"USD":"4.4160000000","CNY":""}},{"instanceType":"m5zn.large","region":"sa-east-1","priceModel":"onDemand","vcpu":2,"memory":8,"unit":"Hrs","pricePerUnit":{"USD":"0.2632000000","CNY":""}},{"instanceType":"m5ad.2xlarge","region":"sa-east-1","priceModel":"onDemand","vcpu":8,"memory":32,"unit":"Hrs","pricePerUnit":{"USD":"0.6600000000","CNY":""}},{"instanceType":"c5a.xlarge","region":"sa-east-1","priceModel":"onDemand","vcpu":4,"memory":8,"unit":"Hrs","pricePerUnit":{"USD":"0.2360000000","CNY":""}},{"instanceType":"c5d.xlarge","region":"sa-east-1","priceModel":"onDemand","vcpu":4,"memory":8,"unit":"Hrs","pricePerUnit":{"USD":"0.2980000000","CNY":""}},{"instanceType":"i3.xlarge","region":"sa-east-1","priceModel":"onDemand","vcpu":4,"memory":30.5,"unit":"Hrs","pricePerUnit":{"USD":"0.4980000000","CNY":""}},{"instanceType":"i4i.8xlarge","region":"sa-east-1","priceModel":"onDemand","vcpu":32,"memory":256,"unit":"Hrs","pricePerUnit":{"USD":"4.3820000000","CNY":""}},{"instanceType":"c6in.32xlarge","region":"sa-east-1","priceModel":"onDemand","vcpu":128,"memory":256,"unit":"Hrs","pricePerUnit":{"USD":"11.1552000000","CNY":""}},{"instanceType":"g5.48xlarge","region":"sa-east-1","priceModel":"onDemand","vcpu":192,"memory":768,"unit":"Hrs","pricePerUnit":{"USD":"27.6863600000","CNY":""}},{"instanceType":"g5.24xlarge","region":"sa-east-1","priceModel":"onDemand","vcpu":96,"memory":384,"unit":"Hrs","pricePerUnit":{"USD":"13.8431800000","CNY":""}},{"instanceType":"t2.2xlarge","region":"sa-east-1","priceModel":"onDemand","vcpu":8,"memory":32,"unit":"Hrs","pricePerUnit":{"USD":"0.5952000000","CNY":""}},{"instanceType":"c6a.16xlarge","region":"sa-east-1","priceModel":"onDemand","vcpu":64,"memory":128,"unit":"Hrs","pricePerUnit":{"USD":"3.7728000000","CNY":""}},{"instanceType":"c5.large","region":"sa-east-1","priceModel":"onDemand","vcpu":2,"memory":4,"unit":"Hrs","pricePerUnit":{"USD":"0.1310000000","CNY":""}},{"instanceType":"r3.8xlarge","region":"sa-east-1","priceModel":"onDemand","vcpu":32,"memory":244,"unit":"Hrs","pricePerUnit":{"USD":"5.5970000000","CNY":""}},{"instanceType":"c3.large","region":"sa-east-1","priceModel":"onDemand","vcpu":2,"memory":3.75,"unit":"Hrs","pricePerUnit":{"USD":"0.1630000000","CNY":""}},{"instanceType":"i4i.24xlarge","region":"sa-east-1","priceModel":"onDemand","vcpu":96,"memory":768,"unit":"Hrs","pricePerUnit":{"USD":"13.1472000000","CNY":""}},{"instanceType":"c6g.metal","region":"sa-east-1","priceModel":"onDemand","vcpu":64,"memory":128,"unit":"Hrs","pricePerUnit":{"USD":"3.3536000000","CNY":""}},{"instanceType":"r5a.8xlarge","region":"sa-east-1","priceModel":"onDemand","vcpu":32,"memory":256,"unit":"Hrs","pricePerUnit":{"USD":"2.8960000000","CNY":""}},{"instanceType":"c6gn.12xlarge","region":"sa-east-1","priceModel":"onDemand","vcpu":48,"memory":96,"unit":"Hrs","pricePerUnit":{"USD":"3.1920000000","CNY":""}},{"instanceType":"m5.4xlarge","region":"sa-east-1","priceModel":"onDemand","vcpu":16,"memory":64,"unit":"Hrs","pricePerUnit":{"USD":"1.2240000000","CNY":""}},{"instanceType":"c5ad.8xlarge","region":"sa-east-1","priceModel":"onDemand","vcpu":32,"memory":64,"unit":"Hrs","pricePerUnit":{"USD":"2.1440000000","CNY":""}},{"instanceType":"c4.8xlarge","region":"sa-east-1","priceModel":"onDemand","vcpu":36,"memory":60,"unit":"Hrs","pricePerUnit":{"USD":"2.4700000000","CNY":""}},{"instanceType":"c6gd.8xlarge","region":"sa-east-1","priceModel":"onDemand","vcpu":32,"memory":64,"unit":"Hrs","pricePerUnit":{"USD":"1.9040000000","CNY":""}},{"instanceType":"m2.4xlarge","region":"sa-east-1","priceModel":"onDemand","vcpu":8,"memory":68.4,"unit":"Hrs","pricePerUnit":{"USD":"1.2910000000","CNY":""}},{"instanceType":"c6i.metal","region":"sa-east-1","priceModel":"onDemand","vcpu":128,"memory":256,"unit":"Hrs","pricePerUnit":{"USD":"8.3840000000","CNY":""}},{"instanceType":"x1.32xlarge","region":"sa-east-1","priceModel":"onDemand","vcpu":128,"memory":1952,"unit":"Hrs","pricePerUnit":{"USD":"26.0100000000","CNY":""}},{"instanceType":"r6gd.2xlarge","region":"sa-east-1","priceModel":"onDemand","vcpu":8,"memory":64,"unit":"Hrs","pricePerUnit":{"USD":"0.7296000000","CNY":""}},{"instanceType":"c4.large","region":"sa-east-1","priceModel":"onDemand","vcpu":2,"memory":3.75,"unit":"Hrs","pricePerUnit":{"USD":"0.1550000000","CNY":""}},{"instanceType":"r6i.large","region":"sa-east-1","priceModel":"onDemand","vcpu":2,"memory":16,"unit":"Hrs","pricePerUnit":{"USD":"0.2010000000","CNY":""}},{"instanceType":"c5a.12xlarge","region":"sa-east-1","priceModel":"onDemand","vcpu":48,"memory":96,"unit":"Hrs","pricePerUnit":{"USD":"2.8320000000","CNY":""}},{"instanceType":"r5d.2xlarge","region":"sa-east-1","priceModel":"onDemand","vcpu":8,"memory":64,"unit":"Hrs","pricePerUnit":{"USD":"0.9120000000","CNY":""}},{"instanceType":"r5b.12xlarge","region":"sa-east-1","priceModel":"onDemand","vcpu":48,"memory":384,"unit":"Hrs","pricePerUnit":{"USD":"5.6880000000","CNY":""}},{"instanceType":"r6g.8xlarge","region":"sa-east-1","priceModel":"onDemand","vcpu":32,"memory":256,"unit":"Hrs","pricePerUnit":{"USD":"2.5728000000","CNY":""}},{"instanceType":"c6a.large","region":"sa-east-1","priceModel":"onDemand","vcpu":2,"memory":4,"unit":"Hrs","pricePerUnit":{"USD":"0.1179000000","CNY":""}},{"instanceType":"i3.large","region":"sa-east-1","priceModel":"onDemand","vcpu":2,"memory":15.25,"unit":"Hrs","pricePerUnit":{"USD":"0.2490000000","CNY":""}},{"instanceType":"r5d.4xlarge","region":"sa-east-1","priceModel":"onDemand","vcpu":16,"memory":128,"unit":"Hrs","pricePerUnit":{"USD":"1.8240000000","CNY":""}},{"instanceType":"m6g.metal","region":"sa-east-1","priceModel":"onDemand","vcpu":64,"memory":256,"unit":"Hrs","pricePerUnit":{"USD":"3.9168000000","CNY":""}},{"instanceType":"m5ad.16xlarge","region":"sa-east-1","priceModel":"onDemand","vcpu":64,"memory":256,"unit":"Hrs","pricePerUnit":{"USD":"5.2800000000","CNY":""}},{"instanceType":"r5n.8xlarge","region":"sa-east-1","priceModel":"onDemand","vcpu":32,"memory":256,"unit":"Hrs","pricePerUnit":{"USD":"3.7760000000","CNY":""}},{"instanceType":"r5b.2xlarge","region":"sa-east-1","priceModel":"onDemand","vcpu":8,"memory":64,"unit":"Hrs","pricePerUnit":{"USD":"0.9480000000","CNY":""}},{"instanceType":"m5.metal","region":"sa-east-1","priceModel":"onDemand","vcpu":96,"memory":384,"unit":"Hrs","pricePerUnit":{"USD":"7.3440000000","CNY":""}},{"instanceType":"m4.16xlarge","region":"sa-east-1","priceModel":"onDemand","vcpu":64,"memory":256,"unit":"Hrs","pricePerUnit":{"USD":"5.0880000000","CNY":""}},{"instanceType":"c6a.4xlarge","region":"sa-east-1","priceModel":"onDemand","vcpu":16,"memory":32,"unit":"Hrs","pricePerUnit":{"USD":"0.9432000000","CNY":""}},{"instanceType":"c6gd.16xlarge","region":"sa-east-1","priceModel":"onDemand","vcpu":64,"memory":128,"unit":"Hrs","pricePerUnit":{"USD":"3.8080000000","CNY":""}},{"instanceType":"c5n.4xlarge","region":"sa-east-1","priceModel":"onDemand","vcpu":16,"memory":42,"unit":"Hrs","pricePerUnit":{"USD":"1.3280000000","CNY":""}},{"instanceType":"m6i.16xlarge","region":"sa-east-1","priceModel":"onDemand","vcpu":64,"memory":256,"unit":"Hrs","pricePerUnit":{"USD":"4.8960000000","CNY":""}},{"instanceType":"g5.8xlarge","region":"sa-east-1","priceModel":"onDemand","vcpu":32,"memory":128,"unit":"Hrs","pricePerUnit":{"USD":"4.1611100000","CNY":""}},{"instanceType":"m6gd.4xlarge","region":"sa-east-1","priceModel":"onDemand","vcpu":16,"memory":64,"unit":"Hrs","pricePerUnit":{"USD":"1.1520000000","CNY":""}},{"instanceType":"c5a.8xlarge","region":"sa-east-1","priceModel":"onDemand","vcpu":32,"memory":64,"unit":"Hrs","pricePerUnit":{"USD":"1.8880000000","CNY":""}},{"instanceType":"m6i.2xlarge","region":"sa-east-1","priceModel":"onDemand","vcpu":8,"memory":32,"unit":"Hrs","pricePerUnit":{"USD":"0.6120000000","CNY":""}},{"instanceType":"c5d.metal","region":"sa-east-1","priceModel":"onDemand","vcpu":96,"memory":192,"unit":"Hrs","pricePerUnit":{"USD":"7.1520000000","CNY":""}},{"instanceType":"c6g.16xlarge","region":"sa-east-1","priceModel":"onDemand","vcpu":64,"memory":128,"unit":"Hrs","pricePerUnit":{"USD":"3.3536000000","CNY":""}},{"instanceType":"x1e.2xlarge","region":"sa-east-1","priceModel":"onDemand","vcpu":8,"memory":244,"unit":"Hrs","pricePerUnit":{"USD":"3.2510000000","CNY":""}},{"instanceType":"c5.18xlarge","region":"sa-east-1","priceModel":"onDemand","vcpu":72,"memory":144,"unit":"Hrs","pricePerUnit":{"USD":"4.7160000000","CNY":""}}]